pl_hub_sparse_ml_callback/__about__.py
pl_hub_sparse_ml_callback/__init__.py
pl_hub_sparse_ml_callback/boring_model.py
pl_hub_sparse_ml_callback/callback.py
pl_hub_sparse_ml_callback/setup_tools.py
pl_hub_sparse_ml_callback-0.0.2.dist-info/LICENSE
pl_hub_sparse_ml_callback-0.0.2.dist-info/METADATA
pl_hub_sparse_ml_callback-0.0.2.dist-info/WHEEL
pl_hub_sparse_ml_callback-0.0.2.dist-info/top_level.txt
pl_hub_sparse_ml_callback-0.0.2.dist-info/RECORD
