Metadata-Version: 2.1
Name: pl-hub-sparse-ml-callback
Version: 0.0.2
Summary: Sparse ML Callback project.
Home-page: https://github.com/tchaton/pl_hub_sparse_ml_callback
Author: tchaton et al.
Author-email: thomas.chaton.ai@gmail.com
License: TBD
Download-URL: https://github.com/tchaton/pl_hub_sparse_ml_callback
Project-URL: Bug Tracker, https://github.com/tchaton/pl_hub_sparse_ml_callback/issues
Project-URL: Documentation, https://pl_hub_sparse_ml_callback.rtfd.io/en/latest/
Project-URL: Source Code, https://github.com/tchaton/pl_hub_sparse_ml_callback
Keywords: deep learning,pytorch,AI
Platform: UNKNOWN
Classifier: Environment :: Console
Classifier: Natural Language :: English
Classifier: Development Status :: 3 - Alpha
Classifier: Intended Audience :: Developers
Classifier: Topic :: Scientific/Engineering :: Artificial Intelligence
Classifier: Topic :: Scientific/Engineering :: Image Recognition
Classifier: Topic :: Scientific/Engineering :: Information Analysis
Classifier: Operating System :: OS Independent
Classifier: Programming Language :: Python :: 3
Classifier: Programming Language :: Python :: 3.6
Classifier: Programming Language :: Python :: 3.7
Classifier: Programming Language :: Python :: 3.8
Requires-Python: >=3.6
License-File: LICENSE
Requires-Dist: torch (<1.8.1)
Requires-Dist: pytorch-lightning (>=1.4.5)
Requires-Dist: sparseml
